README.md
setup.cfg
setup.py
optima/__init__.py
optima/_version.py
optima.egg-info/PKG-INFO
optima.egg-info/SOURCES.txt
optima.egg-info/dependency_links.txt
optima.egg-info/requires.txt
optima.egg-info/top_level.txt