Metadata-Version: 2.1
Name: optima
Version: 0.1.2
Summary: PyTorch Optimization Framework for Researchers
Home-page: https://learnables.github.com/optima
Author: Seb Arnold
Author-email: smr.arnold@gmail.com
License: License :: OSI Approved :: Apache Software License
Download-URL: https://github.com/learnables/optima/archive/0.1.2.zip
Platform: UNKNOWN
